dotmesh/__init__.py
dotmesh/__version__.py
dotmesh/client.py
datadots_api-0.2.1.dist-info/LICENSE
datadots_api-0.2.1.dist-info/METADATA
datadots_api-0.2.1.dist-info/WHEEL
datadots_api-0.2.1.dist-info/top_level.txt
datadots_api-0.2.1.dist-info/RECORD
