Metadata-Version: 2.1
Name: datadots-api
Version: 0.2.1
Summary: Datadots API
Home-page: https://github.com/dotmesh-io/python-sdk
Author: Michael Hausenblas
Author-email: michael.hausenblas@gmail.com
License: UNKNOWN
Platform: UNKNOWN
Requires-Dist: requests
Requires-Dist: jsonrpcclient[requests] (==3.3.4)
